zyp/__init__.py
zyp/__main__.py
zyp/cli.py
zyp/py.typed
zyp-0.0.0.dist-info/LICENSE
zyp-0.0.0.dist-info/METADATA
zyp-0.0.0.dist-info/WHEEL
zyp-0.0.0.dist-info/entry_points.txt
zyp-0.0.0.dist-info/top_level.txt
zyp-0.0.0.dist-info/RECORD
